MANIFEST.in
README.rst
setup.cfg
setup.py
docs/HISTORY.txt
slideshare/__init__.py
slideshare/api.py
slideshare/test_main.py
slideshare.egg-info/PKG-INFO
slideshare.egg-info/SOURCES.txt
slideshare.egg-info/dependency_links.txt
slideshare.egg-info/entry_points.txt
slideshare.egg-info/not-zip-safe
slideshare.egg-info/requires.txt
slideshare.egg-info/top_level.txt