Metadata-Version: 1.0
Name: slideshare
Version: 0.1dev
Summary: Slideshare API client
Home-page: https://github.com/cleder/slideshare
Author: Christian Ledermann
Author-email: christian.ledermann@gmail.com
License: LGPL
Keywords: slideshare api rest
Platform: UNKNOWN
